gavaconnect/__init__.py
gavaconnect/py.typed
gavaconnect_sdk_python-0.2.1.dist-info/METADATA
gavaconnect_sdk_python-0.2.1.dist-info/WHEEL
gavaconnect_sdk_python-0.2.1.dist-info/entry_points.txt
gavaconnect_sdk_python-0.2.1.dist-info/RECORD
