Metadata-Version: 2.4
Name: gavaconnect-sdk-python
Version: 0.2.1
Summary: Python SDK for GavaConnect API
Project-URL: Homepage, https://github.com/acoruss/gavaconnect-sdk-python
Project-URL: Repository, https://github.com/acoruss/gavaconnect-sdk-python
Project-URL: Documentation, https://github.com/acoruss/gavaconnect-sdk-python#readme
Project-URL: Issues, https://github.com/acoruss/gavaconnect-sdk-python/issues
Author-email: Acoruss <acoruss+sdks@gmail.com>, Musale Martin <martinmshale@gmail.com>
License: MIT
Keywords: api,gavaconnect,sdk
Classifier: Development Status :: 3 - Alpha
Classifier: Intended Audience :: Developers
Classifier: License :: OSI Approved :: MIT License
Classifier: Programming Language :: Python :: 3
Classifier: Programming Language :: Python :: 3.13
Requires-Python: >=3.13
Provides-Extra: dev
Requires-Dist: bandit>=1.7.0; extra == 'dev'
Requires-Dist: mypy>=1.8.0; extra == 'dev'
Requires-Dist: pytest-cov>=4.0.0; extra == 'dev'
Requires-Dist: pytest>=8.0.0; extra == 'dev'
Requires-Dist: ruff>=0.2.0; extra == 'dev'
